MANIFEST.in
README.rst
setup.py
docs/HISTORY.txt
docs/LICENSE.txt
edw/__init__.py
edw.recipe.responsecheck.egg-info/PKG-INFO
edw.recipe.responsecheck.egg-info/SOURCES.txt
edw.recipe.responsecheck.egg-info/dependency_links.txt
edw.recipe.responsecheck.egg-info/entry_points.txt
edw.recipe.responsecheck.egg-info/namespace_packages.txt
edw.recipe.responsecheck.egg-info/not-zip-safe
edw.recipe.responsecheck.egg-info/requires.txt
edw.recipe.responsecheck.egg-info/top_level.txt
edw/recipe/__init__.py
edw/recipe/responsecheck/__init__.py
edw/recipe/responsecheck/version.txt
edw/recipe/responsecheck/tests/__init__.py
edw/recipe/responsecheck/tests/test_docs.py