Metadata-Version: 1.1
Name: edw.recipe.responsecheck
Version: 1.0
Summary: A recipe that generates bash script for testing connectivity to application servers
Home-page: http://github.com/eaudeweb/edw.recipe.responsecheck
Author: Eau de Web
Author-email: vitalie.maldur@eaudeweb.ro
License: GPL
Keywords: edw recipe zope plone connectivity server
Platform: UNKNOWN
Classifier: Framework :: Zope2
Classifier: Framework :: Zope3
Classifier: Framework :: Plone
Classifier: Intended Audience :: Developers
Classifier: Programming Language :: Python
Classifier: Topic :: Software Development
Classifier: License :: OSI Approved :: GNU General Public License (GPL)
